{
    "andaman and nicobar islands": {
        "south andaman": ["Dr. B. R. Ambedkar Institute of Technology"]
    },
    "andhra pradesh": {
        "amalapuram": ["Srinivasa Institute of Engineering and Technology"],
        "anakapalle": ["Dadi Institute of Engineering & Technology (DIET)"],
        "ananthapuramu": ["Jawaharlal Nehru Technological University"],
        "bapatla": [
            "Bapatla Engineering College",
            "Bapatla Women`s Engineering College"
        ],
        "bhatlapalem": [
            "Bonam Venkata Chalamaiah Institute of Technology and Science"
        ],
        "bhimavaram": [
            "Sagi Ramakrishnam Raju Engineering College",
            "Shri Vishnu Engineering College for Women",
            "Vishnu Institute of Technology"
        ],
        "chebrolu": ["Chebrolu Engineering College"],
        "chirala": ["St Anns College of Engineering and Technology"],
        "chittoor": [
            "M.J.R. College of Engineering & Technology, Pulicherla",
            "Sreenivasa Institute of Technology and Management Studies",
            "Sri Venkateswara College of Engineering & Technology",
            "Vemu Institute of Technology"
        ],
        "eluru": [
            "Ramachandra College of Engineering",
            "SIR C R REDDY COLLEGE OF ENGINEERING"
        ],
        "gooty": ["Gates Institute of Technology"],
        "gudlavalleru": ["Gudlavalleru Engineering College"],
        "gudur": [
            "Audisankara College of Engineering & Technology",
            "Narayana Engineering College"
        ],
        "guntur": [
            "Chalapathi Institute of Engineering and Technology",
            "Eswar College of Engineering",
            "Kallam Haranadhareddy Institute of Technology",
            "KKR&KSR Institute of Technology & Sciences, VINJANAMPADU Village (CC-JR)",
            "R. V. R. & J. C. College of Engineering",
            "Sri Mittapalli College of Engineering",
            "Sri Mittapalli Institute of Technology for Women",
            "Tirumala Engineering College, Jonnalagadda(Post), Narasaraopet, PIN-522601(CC-NE)",
            "Vasireddy Venkatadri Institute of Technology",
            "Vignan's Foundation for Science, Technology and Research"
        ],
        "kadapa": [
            "Annamacharya Institute of Technology and Sciences",
            "K. S. R. M. College of Engineering",
            "Sri Venkateswara College of Engineering"
        ],
        "kakinada": ["Jawaharlal Nehru Technological University"],
        "kanchikacherla": ["MVR College of Engineering and Technology"],
        "kavali": [
            "Parvathareddy Babulreddy Visvodaya Institute of Technology and Science"
        ],
        "kodavaluru": ["Sree Venkateswara College of Engineering"],
        "krishna": [
            "Devineni Venkata Ramana & Dr. Hima Sekhar MIC College of Technology",
            "Sree Vahini Institute of Science & Technology, Sai Vihini nagar Bypass Road, Tiruvur, PIN-521 235.(CC-MG)",
            "Usha Rama College of Engineering & Technology",
            "Vikas College of Engineering and Technology, Nunna, Vijayawada (Rural), PIN-521212(CC-NQ)"
        ],
        "kuppam": ["Kuppam Engineering College"],
        "kurnool": [
            "Dr.K.V.Subba Reddy Institute of Technology, Kurnool",
            "G. Pullaiah College of Engineering and Technology",
            "G.Pulla Reddy Engineering College",
            "India Institute of Information Technology Design and Manufacturing, Kurnool",
            "Ravindra College of Engineering for Women"
        ],
        "machilipatnam": [
            "Daita Madhusudana Sastry Sri Venkateswara Hindu College of Engineering"
        ],
        "madanapalle": [
            "Aditya College of Engineering",
            "Madanapalle Institute of Technology & Science",
            "Viswam Engineering College"
        ],
        "markapur": ["Dr. Samuel George Institute of Engineering & Technology"],
        "mylavaram": ["Lakireddy Bali Reddy College of Engineering"],
        "nandyal": [
            "RAJEEV GANDHI MEMORIAL COLLEGE OF ENGINEERING & TECHNOLOGY",
            "Santhiram Engineering College",
            "SVR Engineering College, Nandyal"
        ],
        "narasaraopet": [
            "A. M. Reddy Memorial College of Engineering and Technology",
            "Narasaraopeta Engineering College",
            "Narasaraopeta Institute of Technology, Kotappakonda Road, Yellamanda(P.O), Narasaraopet, PIN-522601 (CC-KH)"
        ],
        "narsapur": ["SWARNANDHRA COLLEGE OF ENGINEERING & TECHNOLOGY"],
        "nellore": [
            "GEETHANJALI INSTITUTE OF SCIENCE AND TECHNOLOGY",
            "Narayana Engineering College"
        ],
        "nuzvid": [
            "Rajiv Gandhi University of Knowledge Technologies",
            "Sri Sarathi Institute of Engineering & Technoology"
        ],
        "odalarevu": ["Bonam Venkata Chalamayya Engineering College"],
        "ongole": [
            "PACE INSTITUTE OF TECHNOLOGY AND SCIENCES",
            "QIS College of Engineering & Technology"
        ],
        "palamaner": ["Mother Theresa Institute of Engineering and Technology"],
        "pedana": ["Sri Vasavi Institute of Engineering & Technology"],
        "proddatur": [
            "GOUTHAMI INSTITUTE OF TECHNOLOGY & MANAGEMENT FOR WOMEN",
            "Sai Rajeswari Institute Of Technology",
            "Vaagdevi Institute of Technology and Science"
        ],
        "puttaparthi": ["Sanskrithi School of Engineering"],
        "puttur": [
            "SIDDARTHA INSTITUTE OF SCIENCE AND TECHNOLOGY",
            "Siddharth Institute of Engineering & Technology",
            "Sri Venkatesa Perumal College of Engineering & Technology"
        ],
        "rajahmundry": [
            "Adikavi Nannaya University",
            "Godavari Institute of Engineering & Technology"
        ],
        "rajam": ["GMR Institute of Technology"],
        "rajampet": ["ANNAMACHARYA INSTITUTE OF TECHNOLOGY & SCIENCES"],
        "rotarypuram village": ["Srinivasa Ramanujan Institute of Technology"],
        "sullurupeta": ["Gokula Krishna College of Engineering"],
        "surampalem": [
            "Aditya College of Engineering",
            "Aditya College of Engineering & Technology",
            "Aditya Engineering College",
            "Pragati Engineering College"
        ],
        "tadepalligudem": [
            "Sasi Institute of Technology & Engineering",
            "Sri Vasavi Engineering College"
        ],
        "tekkali": ["Aditya Institute of Technology and Management"],
        "tirupathi": [
            "Siddartha Educational Academy Group of Institutions (Integrated Campus)",
            "Sri Padmavathi Mahila Visvavidyalayam"
        ],
        "tirupati": ["Sree Rama Engineering College"],
        "udayagiri": ["MRR Institute of Technology & Science"],
        "vaddeswaram": [
            "Koneru Lakshmaiah Education Foundation University (K L College of Engineering)"
        ],
        "vadlamudi": ["Vignan`s Lara Institute of Technology & Science"],
        "vempalli": ["RGUKT- RK Valley"],
        "vidyanagar": ["N. B. K. R. Institute of Science & Technology"],
        "vijayawada": [
            "Potti Sriramulu College of Engineering & Technology, D.No.7-3-6/1, Raghava Reddy Street, Kotha Peta, Vijayawada, PIN- 520 001.(CC-KT)",
            "SRK Institute of Technology, Enikepadu",
            "Velagapudi Ramakrishna Siddhartha Engineering College"
        ],
        "visakhapatnam": [
            "Anil Neerukonda Institute of Technology & Sciences",
            "AU College of Engineering (A)",
            "Dr. Lankapalli Bullayya College of Engineering",
            "Gandhi Institute of Technology and Management",
            "Gayatri Vidya Parishad College for Degree and P.G Courses (Autonomous)",
            "Gayatri Vidya Parishad College of Engineering",
            "Gayatri Vidya Parishad College of Engineering for Women",
            "Nadimpalli Satyanarayana Raju Institute of Technology",
            "Raghu Engineering College",
            "Sanketika Vidya Parishad Engineering College",
            "Vignan`s Institute of Information Technology",
            "Wellfare Institute of Science, Technology and Management"
        ],
        "vizianagaram": [
            "Lendi Institute of Engineering & Technology",
            "Maharaj Vijayaram Gajapathi Raj College of Engineering",
            "University College of Engineering"
        ],
        "west godavari": ["D. N. R. College of Engineering & Technology"],
        "yerpedu": ["INDIAN INSTITUTE OF TECHNOLOGY, TIRUPATI"]
    },
    "arunachal pradesh": {
        "itanagar": [
            "National Institute of Technology Arunachal Pradesh",
            "North Eastern Regional Institute of Science & Technology"
        ]
    },
    "assam": {
        "azara": ["Assam Don Bosco University"],
        "dibrugarh": [
            "DIBRUGARH UNIVERSITY INSTITUTE OF ENGINEERING AND TECHNOLOGY"
        ],
        "guwahati": [
            "Assam Down Town University",
            "Indian Institute of Information Technology Guwahati",
            "Indian Institute of Technology Guwahati"
        ],
        "kamrup": [
            "Assam Engineering College",
            "Girijananda Chowdhury Institute of Management & Technology"
        ],
        "kokrajhar": ["Central Institute of Technology"],
        "silchar": ["National Institute of Technology Silchar"],
        "tezpur": ["Tezpur University"]
    },
    "bihar": {
        "begusarai": [
            "Rashtrakavi Ramdhari Singh Dinkar College of Engineering"
        ],
        "bhagalpur": ["Bhagalpur College of Engineering"],
        "chapra": ["Lok Nayak Jai Prakash Institute of Technology"],
        "darbhanga": [
            "Darbhanga College of Engineering",
            "Lalit Narayan Mithila University, Darbhanga"
        ],
        "gaya": ["Gaya College of Engineering"],
        "katihar": ["Katihar Engineering College"],
        "madhepura": ["B. P. Mandal College of Engineering, Madhepura"],
        "muzaffarpur": ["Muzaffarpur Institute of Technology"],
        "nalanda": ["Nalanda College of Engineering"],
        "patna": [
            "Indian Institute of Technology Patna",
            "National Institute of Technology Patna"
        ],
        "pupri": ["Sitamarhi Institute of Technology"],
        "purba champaran": ["Motihari College of Engineering"],
        "purnea": ["M.I.T., Rambagh"],
        "purnia": ["Vidya Vihar Institute of Technology"],
        "sasaram": ["Sershah Engineering College, Sasaram"]
    },
    "chandigarh": {
        "chandigarh": [
            "Chandigarh College of Engineering & Technology",
            "Panjab University",
            "Punjab Engineering College (Deemed to be University), Chandigarh"
        ]
    },
    "chhattisgarh": {
        "ambikapur": [
            "VISHWAVIDYALAYA ENGINEERING COLLEGE, AMBIKAPUR (A CONSTITUENT COLLEGE OF CSVTU, BHILAI)"
        ],
        "bhilai": [
            "Rungta College of Engineering & Technology",
            "Shri Shankaracharya Technical Campus"
        ],
        "bilaspur": [
            "Chouksey Engineering College",
            "Government Engineering College Bilaspur"
        ],
        "bilaspur (chhattisgarh)": ["Guru Ghasidas Vishwavidyalaya"],
        "durg": [
            "Bhilai Institute of Technology",
            "Chhatrapati Shivaji Institute of Technology Kolihapuri"
        ],
        "jagdalpur": ["Government Engineering College, Jagdalpur"],
        "raigarh": ["OP Jindal University"],
        "raipur": ["ITM University"]
    },
    "delhi": {
        "delhi": [
            "Bhagwan Parshuram Institute of Technology",
            "Indira Gandhi Delhi Technical University for Women",
            "Maharaja Agrasen Institute of Technology",
            "National Institute of Technology Delhi"
        ],
        "east delhi": [
            "Dr Akhilesh Das Gupta Institute of Technology & Management"
        ],
        "new delhi": [
            "BHARATI VIDYAPEETH'S COLLEGE OF ENGINEERING",
            "Guru Gobind Singh Indraprastha University",
            "Indian Institute of Technology Delhi",
            "Indraprastha Institute of Information Technology Delhi",
            "Jamia Hamdard",
            "Jamia Millia Islamia",
            "Maharaja Surajmal Institute of Technology"
        ],
        "north west": [
            "Delhi Technological University",
            "HMR Institute of Technology & Management"
        ],
        "south west": ["Netaji Subhas University of Technology (NSUT)"]
    },
    "goa": {
        "assagao": ["Agnel Institute of Technology and Design"],
        "ponda": [
            "Goa College of Engineering (Government of Goa)",
            "National Institute of Technology Goa"
        ],
        "south goa": ["DON BOSCO COLLEGE OF ENGINEERING, FATORDA, MARGAO"],
        "verna": ["Padre Conceicao College of Engineering"]
    },
    "gujarat": {
        "ahmadabad": [
            "Aditya Silver Oak Institute of Technology",
            "L.J.Institue of Engineering and technology (SFI)-Ahmedabad 032"
        ],
        "ahmedabad": [
            "AHMEDABAD INSTITUTE OF TECH, AHMEDABAD 002",
            "Gujarat Technological University",
            "Institute of Infrastructure Technology Research and Management (IITRAM)",
            "L.D.College of Engineering, Ahmedabad 028.",
            "Nirma University",
            "SAL INSTITUTE OF TECHNOLOGY & ENGINEERING RESEARCH"
        ],
        "anand": [
            "A. D. Patel Institute of Technology",
            "SARDAR PATEL COLLEGE OF ENGINEERING"
        ],
        "bardoli": ["Chhotubhai Gopalbhai Patel Institute of Technology"],
        "bharuch": ["Government Engineering College"],
        "bhavnagar": ["Shantilal Shah Engineering College"],
        "changa": ["Chandubhai S. Patel Institute of Technology"],
        "dohad": ["Government Engineering College"],
        "gandhinagar": [
            "Dhirubhai Ambani Institute of Information and Communication Technology",
            "Indian Institute of Technology Gandhinagar",
            "Indus University",
            "Pandit Deendayal Energy University"
        ],
        "ganpat vidyanagar, mehsana": ["Ganpat University"],
        "godhra": ["Government Engineering College"],
        "kalol-382721": ["Swaminarayan College of Engineering and Technology"],
        "mehsana": ["GUJARAT POWER ENGINEERING & RESEARCH INSTITUTE (104)"],
        "modasa": ["Government Engineering College, Modasa"],
        "morbi": ["Lukhdhirji Engineering College"],
        "moti bhoyan": ["GANDHINAGAR INSTITUTE OF TECHNOLOGY"],
        "nadiad": ["Dharmsinh Desai University"],
        "navsari": ["G. I. D. C. Degree Enginering College"],
        "new vallabh vidyanagar": [
            "Madhuben and Bhanubhai Patel Institute of Technology"
        ],
        "palanpur": ["Government Engineering College"],
        "porbandar": ["DR. V. R. GODHANIA COLLEGE OFENGINEERING & TECHNOLOGY"],
        "rajkot": [
            "Darshan Institute of Engineering & Technology",
            "Government Engineering College",
            "Marwadi University"
        ],
        "siddhpur": ["Gokul Global University"],
        "surat": ["VIDHYADEEP INSTITUTE OF ENGINEERING AND TECHNOLOGY, 094"],
        "vadodara": [
            "Krishna School of Emerging Technology & Applied Research"
        ],
        "valia": ["Shroff S. R. Rotary Institute of Chemical Technology"],
        "vallabh vidyanagar": [
            "Birla Vishvakarma Mahavidyalaya",
            "G H PATEL COLLEGE OF ENGINEERING & TECHNOLOGY"
        ],
        "valsad": [
            "GOVERNMENT ENGINEERING COLLEGE, VALSAD 019",
            "Laxmi Institute of Technology, Valsad"
        ],
        "visnagar": ["Sankalchand Patel University, Visnagar"]
    },
    "haryana": {
        "ambala": ["Maharishi Markandeshwar"],
        "ambala cantt -133101": [
            "Ambala College of Engineering & Applied Research"
        ],
        "faridabad": [
            "J. C. Bose University of Science and Technology, YMCA",
            "Manav Rachna International Institute of Research & Studies",
            "Manav Rachna University"
        ],
        "gurgaon": [
            "Dronacharya College of Engineering",
            "G. D. Goenka University",
            "Global Institute of Technology & Management"
        ],
        "gurugram": ["K. R. Mangalam University", "The Northcap University"],
        "gurugram, haryana": ["Amity University Haryana, Gurgaon"],
        "hisar": [
            "College of Agricultural Engineering & Technology",
            "Guru Jambheshwar University of Science and Technology, Hissar"
        ],
        "jhajjar": [
            "Delhi Global Institute of Technology",
            "Ganga Institute of Technology & Management"
        ],
        "kurukshetra": [
            "Kurukshetra University",
            "National Institute of Technology Kurukshetra"
        ],
        "mahendergarh": ["Central University of Haryana"],
        "panipat": [
            "Asia Pacific Institute of Information Technology",
            "Panipat Institute of Engineering & Technology"
        ],
        "radaur-135133": [
            "JAI PARKASH MUKAND LAL INNOVATIVE ENGINEERING AND TECHNOLOGY INSTITUTE"
        ],
        "rohtak": ["Maharshi Dayanand University, Rohtak"],
        "sirsa": ["Ch. Devi Lal State Institute of Engineering"],
        "sonepat": ["SRM University Delhi - NCR"],
        "sonipat": [
            "Bhagat Phool Singh Mahila Vishwavidyalaya (WOMEN UNIVERSITY)",
            "Deenbandhu Chhotu Ram University of Science & Technology",
            "National Institute of Food Technology, Enterprenurship & Management"
        ],
        "yamunanagar": [
            "Seth Jai Parkash Mukand Lal Inst. of Engineering & Technology"
        ]
    },
    "himachal pradesh": {
        "hamirpur": ["National Institute of Technology Hamirpur"],
        "kala-amb": [
            "Himalayan Institute of Engineering & Technology, Sadhoura Road, Kala Amb. Distt Sirmour"
        ],
        "kangra": ["Rajiv Gandhi Govt. Engineering College"],
        "mandi": [
            "Indian Institute of Technology Mandi",
            "Jawaharlal Nehru Govt.Engineering College"
        ],
        "shimla": ["GOVT. ENGINEERING COLLEGE KOTLA (JEORI)"],
        "solan": [
            "Baddi University of Emerging Sciences and Technology, Baddi (Makhnumajra), Solan",
            "Chitkara University",
            "Jaypee University of Information Technology",
            "Shoolini University of Biotechnology and Management Sciences"
        ],
        "una": [
            "K.C. Education and Socail Welfare Society Group of Research & Professional Institutes, VPO pandoga, Uparla Tehsil & Distt Una"
        ]
    },
    "jammu and kashmir": {
        "baramula": ["SSM College of Engineering"],
        "jammu": [
            "Government College of Engineering & Technology",
            "Indian Institute of Technology Jammu",
            "Model Institute of Engineering and Technology"
        ],
        "katra": ["Shri Mata Vaishno Devi University"],
        "pulwama": ["Islamic University of Science & Technology, Pulwama"],
        "rajouri": ["Baba Ghulam Shah Badshah University"],
        "srinagar": ["National Institute of Technology Srinagar"]
    },
    "jharkhand": {
        "bokaro": ["Guru Gobind Singh Educational Society's Technical Campus"],
        "chaibasa": ["Techno India Chaibasa"],
        "dhanbad": [
            "B I T SINDRI",
            "Indian Institute of Technology (Indian School of Mines)"
        ],
        "dumka": [
            "Dumka Engineering College(ESTD. By Govt. of Jharkhand & Run by Techno India under PPP)"
        ],
        "hazaribag": ["Vinoba Bhave University"],
        "jamshedpur": ["National Institute of Technology, Jamshedpur"],
        "purbi singhbhum": ["R.V.S Engineering College, Jamshedpur"],
        "ramgarh": ["Techno India Ramgarh"],
        "ranchi": [
            "Birla Institute of Technology",
            "Cambridge Institute of Technology",
            "National Institute of Advanced Manufacturing Technology, Ranchi",
            "RTC Institute of Technology",
            "The Institute of Chartered Financial Analysts of India University, Jharkhand"
        ]
    },
    "karnataka": {
        "bagalkot": ["Basaveshwar Engineering College"],
        "ballari": ["Rao Bahaddur Y Mahabaleshwarappa Engineering College"],
        "bangalore": [
            "Adarsha Institute of Technology, Lingadjeera Gollahalli, Devanahalli",
            "Bangalore Institute of Technology, Bangalore",
            "Bangalore University",
            "City Engineering College, BANGALORE",
            "M.S. Ramaiah University of Applied Sciences",
            "Sambhram Institute of Technology",
            "SEA College of Engineering & Technology, BANGALORE",
            "Sri Krishana Institute of Technology, BANGALORE",
            "University Visvesvaraya College of Engineering"
        ],
        "bangalore rural": ["Vivekananda Institute of Technology, Bangalore"],
        "bantakal": [
            "SHRI MADHWA VADIRAJA INSTITUTE OF TECHNOLOGY AND MANAGEMENT"
        ],
        "belagavi": [
            "Angadi Instittute of Technology and Management",
            "Gogte Institute of Technology, BELGAUM"
        ],
        "belgaum": [
            "Jain College of Engineering, BELGAUM",
            "Visvesvaraya Technological University"
        ],
        "bellary": [
            "Ballari Institute of Technology & Management",
            "Proudadevaraya Institute of Technology, HOSPET"
        ],
        "bengaluru": [
            "Acharya Institute of Technology",
            "ACS COLLEGE OF ENGINEERING",
            "Alliance University",
            "Atria Institute of Technology",
            "B.M.S. College of Engineering",
            "BMS Institute of Technology & Management",
            "BNM INSTITUTE OF TECHNOLOGY",
            "C M R Institute of Technology",
            "Cambridge Institute of Technology",
            "Christ University",
            "Dayananda Sagar Academy of Technology & Management Technical Campus",
            "Dayananda Sagar College of Engineering",
            "Dayananda Sagar University",
            "Don Bosco Institute of Technology, BANGALORE",
            "Dr. Ambedkar Institute of Technology",
            "East West Institute of Technology",
            "Global Academy of Technology",
            "GOPALAN COLLEGE OF ENGINEERING AND MANAGEMENT",
            "International Institute of Information Technology Bangalore",
            "Jain university,Bangalore",
            "JSS academy of Technical Education",
            "JYOTHY INSTITUTE OF TECHNOLOGY",
            "K S Institute of Technology, BANGALORE",
            "K.S. School of Engineering and Management",
            "M.S. Ramaiah Institute of Technology",
            "MVJ College of Engineering",
            "Nagarjuna College of Engg. & Technology, BANGALORE",
            "New Horizon College of Engineering",
            "Nitte Meenakshi Institute of Technology",
            "PES University",
            "Presidency University , Bengaluru",
            "R. N. S. Institute of Technology",
            "R. R. Institute of Technology",
            "R.V. College of Engineering",
            "Reva University",
            "Sai Vidya Institute of Technology",
            "Sir M Visvesvaraya Institute of Technology, BANGALORE",
            "SJB Institute Of Technology",
            "Sri Sairam College of Engineering",
            "SRI VENKATESHWARA COLLEGE OF ENGINEERING",
            "T John Institute Of Technology",
            "The Oxford College of Engineering",
            "Vemana Institute of Technology"
        ],
        "bidar": ["Guru Nanak Dev Engineering College, BIDAR"],
        "chickballapur": ["S J C INSTITUTE OF TECHNOLOGY"],
        "chikmagalur": ["Adichunchanagiri Institute of Technology"],
        "chikodi": ["KLE Society`s College of Engineering & Technology"],
        "dakshina kannada": [
            "Alvas Institute of Engineering and Technology, MOODBIDRI",
            "Srinivas University"
        ],
        "davanagere": ["JAIN INSTITUTE OF TECHNOLOGY, DAVANAGERE"],
        "davangere": ["BAPUJI INSTITUTE OF ENGINEERING & TECHNOLOGY"],
        "dharwad": [
            "Indian Institute of Information Technology, Dharwad",
            "Indian Institute Of Technology Dharwad",
            "KLE Technological University",
            "S. D. M. College of Engineering & Technology"
        ],
        "haliyal": [
            "KLS Vishwanathrao Deshpande Institute of Technology, Haliyal"
        ],
        "hassan": [
            "Govt. Engineering College, Hassan",
            "Malnad College of Engineering, HASSAN"
        ],
        "haveri": ["Government Engineering College"],
        "hubballi": ["K.L.E.INSTITUTE OF TECHNOLOGY"],
        "kalaburagi": [
            "P D A College of Engineering, GULBARGA",
            "Sharnbasva University"
        ],
        "kgf": ["Dr. T. Thimmaiah Institute of Technology"],
        "laxmeshwar": [
            "Smt. Kamala & Vekappa M Agadi College of Engg. & Technology, Lakshmeshwara"
        ],
        "mandya": [
            "B. G. S. Institute of Technology",
            "G. Madegowda Institute of Technology",
            "Maharaja Institute of Tech., Mysore",
            "P E S College of Engineering, MANDYA"
        ],
        "mangaluru": [
            "A J Institute of Engineering and Technology Mangaluru",
            "Canara Engineering College",
            "Mangalore Institute of Technology & Engineering",
            "St. Joseph Engineering College"
        ],
        "manipal": ["MANIPAL INSTITUTE OF TECHNOLOGY"],
        "mysore": [
            "ATME College of Engineering",
            "Vidya Vikas Institute of Engineering & Technology"
        ],
        "mysuru": [
            "G S S S Institute of Engineering & Technology for Women, MYSORE",
            "JSS Science and Technology University",
            "Maharaja Institute of Technology, Thandavapura",
            "The National Institute of Engineering",
            "Vidyavardhaka College of Engineering, MYSORE"
        ],
        "nidasoshi": ["Hirasugar Instiute of Technology"],
        "nitte, udupi": ["NMAM Institute of Technology"],
        "ponnampet": ["Coorg Institute of Technology"],
        "puttur": ["Vivekananda College of Engg. & Tech., PUTTUR"],
        "raichur": ["HKE`s SLN College of Engineering"],
        "ramanagara": ["Govt. Engineering College, RAMANAGARA"],
        "shimoga": [
            "J. N. N. College of Engineering",
            "PES Institute of Technology & Management, SHIVAMOGA"
        ],
        "shorapur": ["Veerappa Nisty Engineering College, HASNAPUR"],
        "surathkal": ["National Institute of Technology Karnataka, Surathkal"],
        "tumkur": [
            "Kalpataru Institute of Technology, TIPTUR",
            "Siddaganga Institute of Technology",
            "Sri Channabasaveshwara Institute of Technology, GUBBI",
            "Sri Siddhartha Institute of Technology, Tumkur."
        ],
        "ujire": ["SDM INSTITUTE OF TECHNOLOGY UJIRE-574240"],
        "vijayapur": [
            "B.L.D.E.A's V.P. Dr. P.G. Halakatti College of Engg. & Tech., Vijayapur"
        ]
    },
    "kerala": {
        "cherthala": ["College of Engineering, Cherthala"],
        "cochin": [
            "Model Engineering College",
            "SCMS School of Engineering & Technology"
        ],
        "ernakulam": [
            "Federal Institute of Science and Technology (FISAT)",
            "KMEA Engineering College",
            "Mar Athanasius College of Engineering, Kothamangalam, Ernakulam -686 666",
            "Rajagiri School of Engineering and Technology (AUTONOMOUS)",
            "Toc-H Institute of Science and Technology, Arakunnam"
        ],
        "kalady": ["Adi Shankara Institute of Engineering and Technology"],
        "kannur": ["Vimal Jyothi Engineering College"],
        "karunagappally": ["College of Engineering ,Karunagappally"],
        "kochi": ["Albertian Institute of Science and Technology - AISAT"],
        "kollam": [
            "College of Engineering Perumon",
            "T. K. M. Institute of Technology",
            "TKM College of Engineering"
        ],
        "koottanad": [
            "SREEPATHY INSTITUTE OF MANAGEMENT & TECHNOLOGY, VAVANOOR"
        ],
        "kothamangalam": ["Mar Baselios Institute of Technology and Science"],
        "kottayam": [
            "AMAL JYOTHI COLLEGE OF ENGINEERING",
            "College of Engineering",
            "Mangalam College of Engineering, Mangalam Hills, Ettumanoor P.O, Kottayam-686 631",
            "Rajiv Gandhi Institute of Technology",
            "Saintgits College of Engineering"
        ],
        "kozhikode": [
            "GOVT. ENGINEERING COLLEGE, KOZHIKODE",
            "National Institute of Technology Calicut"
        ],
        "malappuram": [
            "ERANAD KNOWLEDGE CITY TECHNICAL CAMPUS, CHERUKULAM, MANJERI",
            "Vedavyasa Institute of Technology"
        ],
        "malappuram district": ["MES Engineering College"],
        "palakkad": [
            "Indian Institute of Technology Palakkad",
            "NSS College of Engineering"
        ],
        "pampady": ["Nehru College of Engineering and Research Centre"],
        "parippally": [
            "Valia Koonambaikulathamma College of Engineering and Technology"
        ],
        "pathanapuram": ["College of Engineering, Pathanapuram"],
        "pattoor": ["Sree Buddha College of Engineering, Pattoor"],
        "peermade": [
            "Mar Baselios Christian College of Engineering & Technology"
        ],
        "puthencruz": ["MUTHOOT INSTITUTE OF TECHNOLOGY AND SCIENCE"],
        "sreekrishnapuram": ["Government Engineering College Sreekrishnapuram"],
        "thiruvananthapuram": [
            "Rajadhani Institute of Engineering and Technology"
        ],
        "thodupuzha": ["University College of Engineering"],
        "thrissur": [
            "Christ College of Engineering",
            "Government Engineering College, Thrissur",
            "Jyothi Engineering College",
            "Vidya Academy of Science & Technology"
        ]
    },
    "madhya pradesh": {
        "balaghat": ["School of Engineering and Technology"],
        "bhopal": [
            "Bansal Institute of Science & Technology, Raisen Road, Kokta, Anand Nagar, Bhopal - 462021",
            "Barkatullah University, Bhopal",
            "Bhabha Engineering Research Institute",
            "I. E. S. College of Technology",
            "I. E. S. Institute of Technology and Management",
            "Indian Institute of Science Education & Research Bhopal",
            "Jagran Lakecity University, Bhopal",
            "Jai Narain College Of Technology",
            "Lakshmi Narain College of Technology",
            "Lakshmi Narain College of Technology & Science",
            "Lakshmi Narain College of Technology Excellence",
            "Maulana Azad National Institute of Technology",
            "NRI Institute of Information Science and Technology",
            "Oriental College of Technology",
            "Oriental Institute of Science and Technology",
            "Rajiv Gandhi Proudyogiki Vishwavidyalaya",
            "RKDF University",
            "Sagar Institute of Research & Technology",
            "Sagar Institute of Science Technology & Research (SISTEC-R)",
            "Sagar Institute of Science Technology and Engineering (SISTec-E), Sikandrabad, Near Ratibad, Bhadbhada Road, Bhopal",
            "Sarvepalli Radhakrishnan University",
            "Sri Satya Sai College of Engineering",
            "Technocrats Institute Of Technology",
            "Technocrats Institute of Technology (Excellence), Anand Nagar, PB No. 24, Post Piplani, BHEL, Bhopal - 462021",
            "Truba Institute of Engineering & Information Technology, Karod-Gandhi Nagar By-Pass Road, Bhopal-462036",
            "Vedica Institute of Technology"
        ],
        "guna": ["Jaypee University of Engineering & Technology"],
        "gwalior": [
            "Amity University, Gwalior",
            "Atal Bihari Vajpayee Indian Institute of Information Technology and Management",
            "Institute of Technology and Management",
            "IPS College of Technology & Management",
            "ITM University",
            "Madhav Institute of Technology and Science, Gole ka Mandir, P.O. Residency, Gwalior-474005"
        ],
        "indore": [
            "Vikrant Institute of Technology and Management, Borkhedi, Behind Veterinary College, AB Road, Indore- 453446"
        ],
        "jabalpur": [
            "Facult Nature CareSangathan's Group of Instiutitions, Near Patan Bypass Road Square, Gram-Raighawa,-Jabalpur-482002",
            "Government Engineering College",
            "Gyan Ganga College of Technology, Jabalpur",
            "Gyan Ganga Institute of Technology & Sciences",
            "Pandit Dwarka Prasad Mishra Indian Institute of Information Technology, Design and Manufacturing (IIITDM) Jabalpur"
        ],
        "raisen": ["Rabindranath Tagore University"],
        "rewa": ["Rewa Engineering College"],
        "sehore": [
            "Sri Satya Sai University of Technology & Medical Sciences, Sehore"
        ],
        "sironja": ["Babulal Tarabai Institute of Research & Technology"],
        "tekanpur": ["Rustamji Institute of Technology"],
        "ujjain": ["Ujjain Engineering College"],
        "vidisha": [
            "Samrat Ashok Technological Institute,Civil Lines, Netaji Subhash Marg, Vidisha"
        ]
    },
    "maharashtra": {
        "akola": ["College of Engineering & Technology"],
        "amravati": [
            "P. R. Pote (Patil) Education & Welfare Trust's Group of Institutions's College of Engineering & Management, Amravati."
        ],
        "ashta": [
            "Annasaheb Dange College of Engineering and Technology, Ashta"
        ],
        "aurangabad": [
            "CSMSS Chh. Shahu College of Engineering",
            "Deogiri Technical Campus for Engineering and Management Studies",
            "Everest Education Society Sanchalit, College of Engineering",
            "Government College of Engineering (Academic Autonomous)",
            "Hi-Tech Institute of Technology",
            "Maharashtra Institute of Technology",
            "Mahatma Gandhi Mission`s Jawaharlal Nehru Engineering College",
            "Shreeyash Pratishthan`s Shreeyash College of Engineering and Technology"
        ],
        "avasari (khurd)": ["Government College of Engineering and Research"],
        "badnera-amravati": [
            "Prof. Ram Meghe Institute of Technology & Research"
        ],
        "baramati": [
            "Vidya Pratishthan's Kamalnayan Bajaj Institute of Engineering & Technology, Baramati, M.I.D.C.road, District - Pune"
        ],
        "budhgaon": [
            "PADMABHOOSHAN VASANTRAODADA PATIL INSTITUTE OF TECHNOLOGY"
        ],
        "chandrapur": [
            "Govt Engineering College, Ballarpur road",
            "Rajiv Gandhi College of Engineering, Research and Technology",
            "SHRI SAI COLLEGE OF ENGINEERING & TECHNOLOGY"
        ],
        "chandwad": [
            "Shri Neminath Jain Brahmacharyashramas College of Engineering, Neminagar, Chandwad, Dist.Nashik 423101"
        ],
        "devrukh": ["Rajendra Mane College of Engineering & Technology"],
        "dhule": [
            "Shri Shivaji Vidya Prasarak Sanstha`s Late Bapusaheb Shivajirao Deore College of Engineering, Dhule"
        ],
        "dombivli": ["SHIVAJIRAO S JONDHALE COLLEGE OF ENGINEERING"],
        "ichalkaranji": [
            "D.K.T.E.SOCIETYs TEXTILE AND ENGINEERING INSTITUTE, ICHALKARANJI"
        ],
        "islampur": [
            "Kasegaon Education Society`s Rajarambapu Institute of Technology"
        ],
        "jalgaon": [
            "GF's Godavari College of Engineering",
            "Government College of Engineering, Jalgaon",
            "Khandesh College Education Society?s College of Engineering and Management, Jalgaon",
            "SSBT's College of Engineering & Technology",
            "University Institute of Chemical Technology"
        ],
        "jalna": [
            "Matsyodari Shikshan Sanstha's College of Engineering and Technology, Jalna"
        ],
        "karad": ["Government College of Engineering"],
        "kashti": [
            "Group of Institutions College of Engineering, A-p. Kashti, Tal. Shrigonda,Dist.Ahmednagar"
        ],
        "kolhapur": [
            "Dr D Y Patil Prathisthan College of Engineering Salokhe-Nagar Kolhapur"
        ],
        "kopargaon": [
            "Sanjivani Rural Education Society's College of Engineering"
        ],
        "latur": ["M.S. Bidwe College of Engineering, Latur"],
        "loni": ["PRAVARA RURAL ENGINEERING COLLEGE"],
        "mahagaon": ["SANT GAJANAN MAHARAJ COLLEGE OF ENGINEERING, KOLHAPUR"],
        "mahiravani": [
            "SF's Sandip Institute of Technology and Research Centre"
        ],
        "malkapur": ["Padmshri Dr.V.B.Kolte College of Engineering, Malkapur"],
        "mumbai": [
            "Amity University, Mumbai",
            "Bharatiya Vidya Bhavan`s Sardar Patel Institute of Technology",
            "Don Bosco Institute Of Technology - Mumbai",
            "Fr. Conceicao Rodrigues College of Engineering",
            "Indian Institute of Technology Bombay",
            "Institute of Chemical Technology",
            "K J Somaiya Institute of Technology",
            "K. J. Somaiya College of Engineering",
            "Sardar Patel College of Engineering",
            "St. Francis Institute of Technology",
            "SVKM`s Narsee Monjee Institute of Management Studies",
            "Thadomal Shahani Engineering College",
            "Thakur College of Engineering & Technology",
            "Usha Mittal Institute of Technology for Women",
            "Vasantdada Patil Pratishthan's College of Engineering and Visual Arts",
            "Veermata Jijabai Technological Institute, (VJTI, Mumbai)",
            "Vidyalankar Institute of Technology Pearl Center",
            "Xavier Institute of Engineering, Mahim, Mumbai - 400016"
        ],
        "mumbai suburban": [
            "ATHARVA COLLEGE OF ENGINEERING",
            "Shah And Anchor Kutchhi Engineering College",
            "Shri Vile Parle Kelavani Mandal`s Dwarkadas J. Sanghvi College of Engineering",
            "Vivekanand Education Society`s Institute of Technology Sindhi Society"
        ],
        "nagpur": ["Indian Institute of Information Technology, Nagpur"],
        "nanded": [
            "M.G.M'S COLLEGE OF ENGINEERING ,NANDED",
            "Shri Guru Gobind Singhji Institute of Engineering and Technology"
        ],
        "nandurbar": ["PSGVPM`s D.N.Patel College of Engineering, Shahada"],
        "nashik": [
            "Brahma Valley College of Engineering & Research Institute, Brahma Valley Campus, Anjaneri, Trimbakeshwar",
            "Gokhale Education Society's R. H. Sapat College of Engineering, Management Studies and Research",
            "K. K. Wagh Institute Of Engineering Education & Research",
            "Kalyani Charitable Trusts Late G.N.Sapkal College of Engineering , Sapkal Knowledge Hub,Kalyani Hills, Anjaneri Vadholi, Tryambakeshwar, Dist.Nashik 422212",
            "MARATHA VIDYA PRASARAK SAMAJ'S KARMAVEER ADV. BABURAO GANPATRAO THAKARE COLLEGE OF ENGINEERING",
            "Matoshri Education Society's Matoshri College of Engineering & Research Centre, At-Po.Eklahare, Tal. & District- Nashik 422105."
        ],
        "navi mumbai": [
            "BHARATI VIDYAPEETH COLLEGE OF ENGINEERING, NAVI MUMBAI",
            "DATTA MEGHE COLLEGE OF ENGINEERING",
            "Fr. C. Rodrigues Institute of Technology",
            "Ramrao Adik Institute of Technology",
            "Saraswati Education Society`s Saraswati College of Engineering",
            "SIES Graduate School of Technology",
            "Terna Public Charitable Trust's Terna Engineering College"
        ],
        "new panvel": ["Anjuman-I-Islam`s Kalsekar Technical Campus"],
        "palghar": [
            "Aldel Education Trust's St. John College of Engineering",
            "Haji Jamaluddin Thim TrustTheem College of Engineering At Village Betegaon Boisar Chikhar Road (N.H.No.8) Near Union Park Boisar(E) Tal Palghar Dist. Thane 401 501",
            "Vidya Vikas Education Trust Universal College of Engineering, Thane"
        ],
        "pandharpur": [
            "SKN SINHAGAD COLLEG OF ENGINEERING KORTI TAL PANDHARPUR DIST-SOLAPUR",
            "SVERI's College of Engineering, Pandharpur"
        ],
        "panhala": ["SANJEEVAN ENGINEERING & TECHNOLOGY INSTITUTE"],
        "pune": [
            "(A.B.M.S.) Akhil Bharatiya Maratha Shikshan Parishad's College of Engineering & Research Address: S. No. 103, Shahu College Campus, Parvati, Taluka: Pune (corporation Area) District: Pune - 411009",
            "Ajeenkya DY Patil School of Engineering",
            "All India Shivaji Memorial Societys College of Engineering, Pune",
            "All India Shri Shivaji Memorial Society`s Institute of Information Technology",
            "Army Institute of Technology",
            "Bharati Vidyapeeth 'S College of Engineering for Women",
            "Bharati Vidyapeeth Deemed University College of Engineering",
            "Bharati Vidyapeeth`s College of Engineering",
            "College of Engineering, Pune",
            "Defence Institute of Advanced Technology",
            "DHOLE PATIL EDUCATION SOCIETY'S, DHOLE PATIL COLLEGE OF ENGINEERING.",
            "Dr D. Y. Patil Pratishthans D.Y. Patil College of Engineering, Akurdi, Pune",
            "Dr. D. Y. Patil Institute of Engineering, Management and Research",
            "Dr. D. Y. Patil Institute of Technology",
            "Dr. Vishwanath Karad MIT World Peace University",
            "Indian Institute of Information Technology, Pune",
            "International Institute of Information Technology (I?IT)",
            "JSPM'S RAJARSHI SHAHU COLLEGE OF ENGINEERING",
            "K. J. S. Educational Institute`s Trinity College of Engineering and Research",
            "Maharshi Karve Stree Shikshan Samstha's Cummins College of Engineering for Women",
            "Marathwada Mitra Mandal College of Engineering Pune",
            "MARATHWADA MITRA MANDAL'S INSTITUTE OF TECHNOLOGY",
            "MIT Academy of Engineering",
            "MIT Art, Design and Technology University, Pune",
            "Modern Education Society`s College of Engineering",
            "Pimpri Chinchwad College of Engineering",
            "Pimpri Chinchwad Education Trust's Pimpri Chinchwad College of Engineering and Research, Laxminagar, Ravet",
            "Progressive Educational Society`s Modern College of Engineering",
            "Pune Vidyarthi Griha's College of Science and Technology",
            "SCTR's Pune Institute of Computer Technology",
            "Shree Chanakya Education Societys Indira College",
            "Shree Ramchandra College of Enginnering",
            "Sinhgad Academy of Engineering",
            "Sinhgad College of Engineering",
            "Sinhgad Technical Education Society`s Sinhgad Institute of Technology",
            "Sinhgad Technical Education Society`s SKN Sinhgad Institute of Technology and Science",
            "SINHGAD TECHNICAL EDUCATION SOCIETYS NBN SINHGAD TECHNICAL INSTITUTES CAMPUS, PUNE",
            "Sinhgad Technical Education Societys Rasiklal M Dhariwal Sinhgad Technical Institutes Campus, Pune",
            "Smt. Kashibai Navale College of Engineering",
            "Vishwakarma Institute of Information Technology",
            "Vishwakarma Institute of Technology",
            "Vishwakarma University, Pune"
        ],
        "raigarh": [
            "Dr. Babasaheb Ambedkar Technological University",
            "Mahatma Education Society's, Pillai HOC College of Engineering and technology",
            "Pillai College of Engineering",
            "VISHWANIKETANs INSTITUTE OF MANAGEMENT ENTREPRENEURSHIP and ENGINEERING TECHNOLOGY"
        ],
        "ratnagiri": [
            "Finolex Academy of Management and Technology",
            "Gharda Foundations Gharda Institute of Technology"
        ],
        "sangamner": ["Amrutvahini College of Engineering, Sangamner"],
        "sangli": [
            "Shri Ambabai Talim Sanstha's Sanjay Bhokre Group of Institutes, Miraj",
            "Walchand College of Engineering"
        ],
        "satara": ["Yashoda Technical campus, Faculty of Engineering, Wadhe"],
        "shegaon": [
            "MAULI GROUP OF INSTITUTIONS, COLLEGE OF ENGINEERING AND TECHNOLOGY",
            "Shri Sant Gajanan Maharaj Engineering College, Shegaon."
        ],
        "shirpur": ["SES'S R.C.PATEL INSTITUTE OF TECHNOLOGY, SHIRPUR"],
        "sindhudurg": [
            "JAYAWANTI BABU FOUNDATION+?-?-?S METROPOLITAN INSTITUTE OF TECHNOLOGY AND MANAGEMENT, SINDHUDURG"
        ],
        "solapur": [
            "A G PATIL INSTITUTE OF TECHNOLOGY 18 2A2 PRATANAGER SOREGON ROAD",
            "Brahmdevdada Mane Institute of Technology",
            "Walchand Institute of Technology"
        ],
        "thane": [
            "A P Shah Institute Of Technology",
            "Koti Vidya Charitable Trusts Alamuri Ratnamala Institute of Engineering & Technology",
            "SHREE L R TIWARI COLLEGE OF ENGINEERING, THANE"
        ],
        "vasai": ["VIDYAVARDHINI'S COLLEGE OF ENGINEERING AND TECHNOLOGY"],
        "velneshwar": [
            "Vidya Prasarak Mandal's Maharshi Parshuram College of Engineering"
        ],
        "warananagar": [
            "Tatyasaheb Kore Institute of Engineering & Technology, WARANANAGAR"
        ],
        "yavatmal": ["Jawaharlal Darda Institute of Engineering & Technology"]
    },
    "state": { "city": ["Name"] },
    "manipur": {
        "imphal": ["National Institute of Technology Manipur"],
        "imphal west": ["Manipur Institute of Technology"]
    },
    "meghalaya": { "shillong": ["National Institute of Technology Meghalaya"] },
    "mizoram": { "aizawl": ["National Institute of Technology Mizoram"] },
    "nagaland": { "dimapur": ["National Institute of Technology Nagaland"] },
    "odisha": {
        "berhampur": [
            "National Institute of Science & Technology",
            "Parala Maharaja Engineering College"
        ],
        "bhubaneswar": ["Kalinga Institute of Industrial Technology"],
        "burla": ["Veer Surendra Sai University of Technology"],
        "cuttack": ["Driems"],
        "damanabhuin": ["Bhubaneswar College Of Engineering"],
        "dhenkanal": [
            "Indira Gandhi Institute of Technology (IGIT), Sarang",
            "Synergy Institute of Engineering & Technology"
        ],
        "gunupur": ["Gandhi Institute of Engineering and Technology"],
        "kalahandi": ["Government College of Engineering"],
        "keonjhar": ["Government College of Engineering"],
        "khordha": ["College of Engineering (CEB), Bhubaneswar"],
        "khurda, bhubaneswar": ["Sophitorium Engineering College"],
        "paralakhemundi": ["Centurion University of Technology and Management"],
        "rourkela": ["National Institute of Technology Rourkela"]
    },
    "pondicherry": {
        "karaikal": [
            "National Institute of Technology Puducherry",
            "Perunthalaivar Kamarajar Institute of Engineering and Technology"
        ],
        "puducherry": [
            "Manakulavinayagar Institute of Technology",
            "Pondicherry Engineering College",
            "Rajiv Gandhi College of Engineering and Technology",
            "Sri Manakula Vinayagar Engineering College"
        ]
    },
    "punjab": {
        "amritsar": [
            "Amritsar College of Engineering & Technology",
            "Khalsa College of Engg. and Technology"
        ],
        "bathinda": [
            "Baba Farid College of Engineering& Technology, Bathinda",
            "Giani Zail Singh Campus College of Engineering & Technology Bathinda",
            "Guru Kashi University",
            "Maharaja Ranjit Singh State Technical University"
        ],
        "fatehgarh sahib": [
            "Baba Banda Singh Bahadur Engineering College, Fatehgarh Sahib",
            "Sri Guru Granth Sahib World University"
        ],
        "firozepur": ["Shaheed Bhagat Singh State University"],
        "gurdaspur": [
            "Beant College Of Engineering & Technology,Gurdaspur",
            "Sri Sai College of Engg and Technology , Badhani"
        ],
        "jalandhar": [
            "CT Institute of Engg. Management and Technology, Shahpur",
            "DAV Institute of Engineering & Technology",
            "Dr. B R Ambedkar National Institute of Technology, Jalandhar"
        ],
        "kapurthala": [
            "G. N. A. University",
            "I.K. Gujral Punjab Technical University"
        ],
        "khanna": ["Gulzar Group of Institutions"],
        "longowal": ["Sant Longowal Institute of Engineering & Technology"],
        "ludhiana": ["Guru Nanak Dev Engineering College"],
        "mandi gobindgarh": ["Desh Bhagat University", "RIMT University"],
        "mohali": [
            "Chandigarh Engineering College-CGC, Landran",
            "Chandigarh University"
        ],
        "pathankot": [
            "Aman Bhalla Institute of Engg. & Tech, Jhakolari, Pathankot"
        ],
        "patiala": [
            "Punjabi University, Patiala",
            "Thapar Institute of Engineering and Technology (Deemed-to-be-university)"
        ],
        "phagwara": ["Lovely Professional University"],
        "rajpura": ["Chitkara University"],
        "ropar": ["Institute of Engg. & Tech, Bhaddal"],
        "rupnagar": ["Indian Institute of Technology Ropar"],
        "sahibzada ajit singh nagar": [
            "Chandigarh Engineering College Jhanjeri",
            "Universal Institute of Engineering & Technology"
        ]
    },
    "rajasthan": {
        "ajmer": [
            "Aryabhatta College Of Engineering And Research Center",
            "Govt. Mahila Engineering College,Ajmer"
        ],
        "banasthali": ["Banasthali Vidyapith"],
        "bharatpur": ["GOVERNMENT ENGINEERING COLLEGE BHARATPUR"],
        "bikaner": ["Engineering College Bikaner"],
        "jaipur": [
            "Amity University Rajasthan,Jaipur",
            "Anand International College of Engineering",
            "Arya College of Engg. & Information Technology, Jaipur",
            "ARYA INSTITUTE OF ENGINEERING & TECHNOLOGY",
            "Global Institute of Technology",
            "J. K. Lakshmipat University",
            "JECRC University",
            "Malaviya National Institute of Technology",
            "Manipal University Jaipur",
            "Poornima Institute of Engineering & Technology,Jaipur",
            "Swami Keshvanand Institute of Technology, Management & Gramothan",
            "The LNM Institute of Information Technology, Jaipur",
            "University of Engineering and Management"
        ],
        "jhalawar": ["Government Engineering College, Jhalawar"],
        "jhunjhunun": [
            "B K Birla Institute of Engineering & Technology, Pilani"
        ],
        "jodhpur": ["MBM University, Jodhpur"],
        "kishangarh": ["Central University of Rajasthan"],
        "kota": [
            "Modi Institute of Technology,Kota",
            "Rajasthan Technical University, Kota"
        ],
        "nathdwara": [
            "Shrinathji Institute of Technology & Engineering, Nathdwara, Rajsamand"
        ],
        "pilani": ["Birla Institute of Technology & Science -Pilani"],
        "udaipur": ["S.S. College of Engineering,Udaipur"]
    },
    "sikkim": {
        "rangpo": ["Sikkim Manipal Institute of Technology (SMIT)"],
        "south sikkim": ["National Institute of Technology Sikkim"]
    },
    "tamil nadu": {
        "annamalainagar": ["Annamalai University"],
        "aruppukottai": ["Sree Sowdambika College of Engineering"],
        "attur": ["Tagore Institute of Engineering and Technology"],
        "avadi": ["St. Peter`s College of Engineering and Technology"],
        "chembarambakkam": [
            "Sree Sastha Institute of Engineering and Technology"
        ],
        "chengalpat": ["Adhiparasakthi Engineering College"],
        "chengalpattu": ["Aarupadai Veedu Institute of Technology"],
        "chengalpet": [
            "Karpaga Vinayaga College of Engineering and Technology"
        ],
        "chennai": [
            "Agni College of Technology",
            "ANAND INSTITUTE OF HIGHER TECHNOLOGY",
            "Anna University",
            "B. S. Abdur Rahman Crescent Institute of Science and Technology",
            "Central Institute of Plastics Engineering and Technology",
            "Chennai Institute of Technology",
            "Dhanalakshmi College of Engineering",
            "Easwari Engineering College",
            "G. K. M. College of Engineering and Technology",
            "Gojan School of Business and Technology",
            "Hindustan Institute of Technology and Science (HITS)",
            "Indian Institute of Information Technology, Design & Manufacturing, Kancheepuram",
            "Indian Institute of Technology Madras",
            "Institute of Food and Dairy Technology",
            "JAYA ENGINEERING COLLEGE",
            "Jaya Sakthi Engineering College",
            "Jeppiaar Engineering College",
            "Jerusalem College of Engineering",
            "KCG College of Technology",
            "Loyola Institute of Technology",
            "Loyola-ICAM College of Engineering and Technology",
            "M. G. R. Educational and Research Institute",
            "Meenakshi Sundararajan Engineering College",
            "New Prince Shri Bhavani College of Engineering and Technology",
            "Rajalakshmi Engineering College",
            "S.R.M. Institute of Science and Technology",
            "Sathyabama Institute of Science and Technology",
            "Saveetha Institute of Medical and Technical Sciences",
            "Sri Sai Ram Institute of Technology",
            "Sriram Engineering College",
            "SRM Valliammai Engineering College",
            "St. Joseph College of Engineering",
            "St. Joseph`s Institute of Technology",
            "Thangavelu Engineering College",
            "Vel Tech High Tech Dr. Rangarajan Dr. Sakunthala Engineering College",
            "Vel Tech Rangarajan Dr. Sagunthala R & D Institute of Science and Technology",
            "Velammal Engineering College",
            "Vels Institute of Science Technology & Advanced Studies (VISTAS)"
        ],
        "cheranmahadevi": ["SCAD College of Engineering and Technology"],
        "coimbatore": [
            "ARJUN COLLEGE OF TECHNOLOGY",
            "Kalaignar Karunanidhi Institute of Technology"
        ],
        "cuddalore": [
            "C K College of Engineering & Technology (Formerly Sri Jayaram Engineering College)",
            "Krishnaswamy College of Engineering"
        ],
        "dindigul": [
            "N.P.R. College of Engineering and Technology, Natham Village, Dindigul",
            "PSNA College of Engineering and Technology, Dindigul",
            "R.V.S.College of Engineering",
            "SSM Institute of Engineering and Technology"
        ],
        "elambalur": ["Roever Engineering College"],
        "erode": [
            "Erode Sengunthar Engineering College",
            "Institute of Road and Transport Technology",
            "Nandha College of Technology",
            "Nandha Engineering College",
            "Shree Venkateshwara Hi-Tech Engineering College",
            "Velalar College of Engineering and Technology"
        ],
        "hosur": [
            "Adhiyamaan College of Engineering(Autonomous)",
            "College of Poultry Production and Management"
        ],
        "kalavakkam": ["Sri Sivasubramaniya Nadar College of Engineering"],
        "kallakurichi": ["Idhaya Engineering College for Women"],
        "kancheepuram": [
            "Academy of Maritime Education and Training",
            "Dhaanish Ahmed College of Engineering",
            "Mohamed Sathak A.J. College of Engineering",
            "Peri Institute of Technology",
            "Prince Shri Venkateshwara Padmavathy Engineering College",
            "Sri Muthukumaran Institute of Technology",
            "Sri Sairam Engineering College",
            "St. Josephs College of Engineering",
            "Tagore Engineering College"
        ],
        "kanchipuram": ["JEPPIAAR INSTITUTE OF TECHNOLOGY"],
        "kangeyam": ["Builders Engineering College"],
        "kanniyakumari": [
            "Arunachala College of Engineering for Women",
            "St. Xavier`s Catholic College of Engineering"
        ],
        "kanyakumari": ["Rohini College of Engineering And Technology"],
        "karur": [
            "Chettinad College of Engineering & Technology",
            "M.Kumarasamy College of Engineering",
            "V. S. B. Engineering College"
        ],
        "koduvilarpatti": ["Theni Kammavar Sangam College of Technology"],
        "kovilpatti": [
            "National Engineering College",
            "Unnamalai Institute of Technology"
        ],
        "krishnagiri": [
            "Er. Perumal Manimekalai College of Engineering",
            "Government College of Engineering",
            "P.S.V.College of Engineering and Technology"
        ],
        "madurai": [
            "KAMARAJ COLLEGE OF ENGINEERING & TECHNOLOGY",
            "Latha Mathavan Engineering College, Madurai",
            "Thiagarajar College of Engineering",
            "Velammal College of Engineering & Technology"
        ],
        "mamallapuram": [
            "Dhanalakshmi Srinivasan College of Engineering and Technology"
        ],
        "mayiladuthurai": ["A.V.C. College of Engineering"],
        "melvisharam": ["C. Abdul Hakeem College of Engineering & Technology"],
        "morai": [
            "Vel Tech Multi Tech Dr.Rangarajan Dr.Sakunthala Engineering College"
        ],
        "nagapattinam": [
            "E.G.S. PILLAY ENGINEERING COLLEGE",
            "Sir Isaac Newton College of Engineering and Technology (New)",
            "Tamil Nadu Dr.J.Jayalalithaa Fisheries University"
        ],
        "nagercoil": [
            "Amrita College of Engineering and Technology, Nagercoil",
            "Annai Vailankanni College of Engineering",
            "Loyola Institute of Technology and Science",
            "Ponjesly College of Engineering",
            "Stella Mary`s College of Engineering",
            "University College of Engineering Nagercoil"
        ],
        "namakkal": [
            "EXCEL ENGINEERING COLLEGE",
            "Gnanamani College of Technology",
            "KSR INSTITUTE FOR ENGINEERING AND TECHNOLOGY, NAMAKKAL",
            "Mahendra Engineering College",
            "Mahendra Institute of Technology",
            "Muthayammal Engineering College",
            "Paavai Engineering College",
            "Selvam College of Technology",
            "SSM College of Engineering",
            "Vivekanandha College of Engineering for Women"
        ],
        "neelamangalam,kallakurichi": [
            "A.K.T. Memorial College of Engineering & Technology"
        ],
        "neelambur": ["Kathir College of Engineering"],
        "perundurai": ["Kongu Engineering College"],
        "pollachi": [
            "Dr. Mahalingam College of Engineering and Technology",
            "P. A. College of Engineering and Technology"
        ],
        "pudukkottai": [
            "Kings College of Engineering",
            "Mount Zion College of Engineering and Technology",
            "Shanmuganathan Engineering College"
        ],
        "ramanathapuram": [
            "Mohamed Sathak Engineering College, Kilakarai",
            "Syed Ammal Engineering College"
        ],
        "salem": [
            "AVS Engineering College",
            "Dhirajlal Gandhi College of Technology",
            "Government College of Engineering",
            "Knowledge Institute of Technology",
            "Mahendra College of Engineering",
            "Narasu?s Sarathy Institute of Technology",
            "Salem College of Engineering and Technology",
            "Sona College of Technology",
            "The Kavery Engineering College",
            "Vinayaka Mission's Kirupananda Variyar Engineering College"
        ],
        "samayapuram": ["K. Ramakrishnan College of Engineering"],
        "sankari": ["SRI SHANMUGHA COLLEGE OF ENGINEERING AND TECHNOLOGY"],
        "sivaganga": [
            "Alagappa Chettiar Government College of Engineering and Technology",
            "K. L. N. College of Engineering"
        ],
        "sivakasi": [
            "AAA COLLEGE OF ENGINEERING AND TECHNOLOGY",
            "Mepco Schlenk Engineering College",
            "P.S.R.R College of Engineering"
        ],
        "sriperumbudur": ["Sri Venkateswaraa College of Technology"],
        "srivilliputtur": ["Kalasalingam Academy of Research and Education"],
        "thanjavur": [
            "Arasu Engineering College",
            "Government College of Engineering Thanjavur",
            "National Institute of Food Technology, Entrepreneurship and Management - Thanjavur (NIFTEM - Thanjavur)",
            "Ponnaiyah Ramajayam Institute of Science & Technology",
            "Shanmugha Arts Science Technology & Research Academy"
        ],
        "thatchanallur - 627 358": [
            "Thamirabharani Engineering College, Tirunelveli"
        ],
        "theni": [
            "Government College of Engineering",
            "Nadar Saraswathi College of Engineering & Technology"
        ],
        "thiruvallur": [
            "Aalim Muhammed Salegh College of Engineering",
            "GRT Institute of Engineering and Technology",
            "J. N. N. Institute of Engineering",
            "Panimalar Engineering College",
            "Prathyusha Engineering College",
            "R. M. K. College of Engineering and Technology",
            "R.M.D Engineering College",
            "R.M.K. Engineering College",
            "Rajalakshmi Institute of Technology",
            "S. A. Engineering College",
            "Velammal Institute of Technology"
        ],
        "thiruvarur": ["Anjalai Ammal Mahalingam Engineering College"],
        "thoothukudi": [
            "Grace College of Engineering",
            "St. Mother Theresa Engineering College",
            "V V College of Engineering"
        ],
        "thuckalay": ["Noorul Islam Centre for Higher Education -Kanyakumari"],
        "tiruchengode": [
            "K. S. R. College of Engineering",
            "K.S.Rangasamy College of Technology",
            "Sengunthar College of Engineering",
            "Sengunthar Engineering College"
        ],
        "tiruchirappalli": [
            "CARE College of Engineering",
            "Indra Ganesan College of Engineering",
            "K. Ramakrishnan College of Technology",
            "KONGUNADU COLLEGE OF ENGINEERING AND TECHNOLOGY",
            "M. A. M. College of Engineering and Technology",
            "M. I. E. T. Engineering College",
            "National Institute of Technology Tiruchirappalli",
            "Saranathan College of Engineering",
            "TRP Engineering College (New)",
            "University College of Engineering, BIT Campus Tiruchirappalli"
        ],
        "tiruchirappalli district": [
            "OAS Institute of Technology and Management Group of Institutions (New)"
        ],
        "tirunelveli": [
            "Francis Xavier Engineering College",
            "Government College of Engineering",
            "PSN College of Engineering and Technology",
            "PSN Engineering College",
            "PSN Institute of Technology & Science",
            "S.Veerasamy Chettiar College of Engineering"
        ],
        "tirupur": ["Jai Shriram Engineering College"],
        "vallam thanjavur": [
            "Periyar Maniammai Institute of Science & Technology"
        ],
        "vellore": [
            "Ganadipathy Tulsi's Engineering College",
            "Global Institute of Engineering and Technology",
            "Vellore Institute of Technology"
        ],
        "viluppuram": [
            "I. F. E. T. College of Engineering",
            "Mailam Engineering College",
            "V.R.S. College Of Engineering and Technology"
        ],
        "virudhunagar": [
            "P. S. R. Engineering College",
            "Ramco Institute of Technology"
        ]
    },
    "telangana": {
        "ananthagiri (v&m)": ["Anurag Engineering College"],
        "hanamkonda": ["Chaitanya (Deemed to be University)"],
        "hanumakonda": ["Kakatiya University"],
        "hyderabad": ["Malla Reddy College of Engineering for women"],
        "ibrahimpatan": ["CVR College of Engineering"],
        "ibrahimpatnam": [
            "Guru Nanak Institute of Technology",
            "Guru Nanak Institutions Technical Campus"
        ],
        "karimnagar": [
            "Kamala Institute of Technology & Science",
            "Sree Chaitanya College of Engineering",
            "Sree Chaitanya Institute of Technological Sciences",
            "Vageswari College of Engineering"
        ],
        "khammam": ["Sai Spurthy Institute of Technology"],
        "medak": ["Padmasri Dr. B.V. Raju Institute of Technology"],
        "medchal malkajgiri": [
            "GEETHANJALI COLLEGE OF ENGINEERING AND TECHNOLOGY"
        ],
        "narsampet": ["Balaji Institute of Technology & Science"],
        "rangareddy": [
            "CMR Engineering College",
            "JB Institute of Engineering & Technology",
            "K. G. Reddy College of Engineering & Technology",
            "Samskruti College of Engineering & Technology",
            "Siddhartha Institute of Engineering & Technology",
            "Sreenidi Institute of Science &Technology",
            "Sri Indu College of Engineering and Technology",
            "Sri Indu Institute of Engineering and Technology",
            "Teegala Krishna Reddy Engineering College",
            "Vardhaman College of Engineering"
        ],
        "sangareddy": ["MNR College of Engineering & Technology"],
        "secunderabad": [
            "Malla Reddy College of Engineering and Technology (Autonomous)",
            "Malla Reddy Institute of Engineering and Technology",
            "Malla Reddy Institute of Technology & Science",
            "Narsimhareddy Engineering College",
            "St. Martin's Engineering College"
        ],
        "warangal": [
            "Kakatiya Institute of Technology & Science",
            "National Institute of Technology Warangal",
            "SR University",
            "SVS Group of Institutions",
            "Vaagdevi College of Engineering"
        ],
        "yadadri-bhuvangiri": ["Vignan Institute of Technology and Science"]
    },
    "tripura": {
        "agartala": [
            "The Institute of Chartered Financial Analysts of India University",
            "Tripura Institute of Technology"
        ],
        "agratala": ["National Institute of Technology Agartala"]
    },
    "uttar pradesh": {
        "agra": [
            "Dayalbagh Educational Institute",
            "Raja Balwant Singh Engineering Technical Campus"
        ],
        "aligarh": ["Aligarh Muslim University"],
        "ambedkar nagar": ["Rajkiya Engineering College, Ambedkar Nagar"],
        "amethi": ["Rajiv Gandhi Institute of Petroleum Technology"],
        "azamgarh": ["Rajkiya Engineering College, Azamgarh"],
        "banda": ["Rajkiya Engineering College Banda"],
        "bareilly": [
            "Mahatama Jyotiba Phule Rohikhand University, Bareilly",
            "Rajshree Institute of Management & Technology",
            "Shri Ram Murti Smarak College of Engineering & Technology"
        ],
        "bhadohi": ["Indian Institute of Carpet Technology"],
        "bijnor": ["Kunwar Satyavira College of Engineering and Management"],
        "gautam buddha nagar": [
            "College of Engineering and Technology, IILM Academy of Higher Learning",
            "Gautam Buddha University"
        ],
        "gautam budh nagar": [
            "Amity University",
            "Galgotias University",
            "Jss Academy Of Technical Education, Noida"
        ],
        "ghaziabad": [
            "ABES Engineering College",
            "ABES INSTITUTE OF TECHNOLOGY, GHAZIABAD",
            "Ajay Kumar Garg Engineering College",
            "Dr. K.N. Modi Institute of Engineering and Technology, Modinagar, Ghaziabad",
            "IMS Engineering College",
            "Inderprastha Engineering College",
            "KIET Group of Institutions",
            "NITRA TECHNICAL CAMPUS",
            "R.D.Engineering College",
            "Raj Kumar Goel Institue of Technology",
            "Raj Kumar Goel Institute of Technology for Women, Ghaziabad",
            "Sanskar College of Engineering & Technology"
        ],
        "gorakhpur": ["Institute of Technology and Management, Gorakhpur"],
        "greater noida": [
            "Accurate Institute of Management & Technology",
            "Dronacharya Group of Institutions",
            "G.L.Bajaj Institute of Technology and Management",
            "Galgotias College of Engineering & Technology",
            "Greater Noida Institute of Technology (Engineering Institute)",
            "I.T.S ENGINEERING COLLEGE",
            "IIMT College Of Engineering",
            "Mangalmay Institute of Engineering and Technology, Greater Noida",
            "Noida Institute of Engineering & Technology",
            "Sharda University"
        ],
        "jaunpur": ["Veer Bahadur Singh Purvanchal University, Jaunpur"],
        "jhansi": ["Bundelkhand University"],
        "kanpur": [
            "Chatrapati Sahuji Maharaj Kanpur University",
            "DR. AMBEDKAR INSTITUTE OF TECHNOLOGY FOR HANDICAPPED, U.P.",
            "Indian Institute of Technology Kanpur",
            "Kanpur Institute of Technology",
            "PRANVEER SINGH INSTITUTE OF TECHNOLOGY, KANPUR",
            "Uttar Pradesh Textile Technology Institute"
        ],
        "kanpur nagar": [
            "Harcourt Butler Technical University",
            "Rama University Uttar Pradesh"
        ],
        "lucknow": [
            "B N College Of Engineering And Technology Lucknow",
            "Bansal Institute of Engineering & Technology,Lucknow",
            "Central Institute of Plastics Engineering & Technology, Lucknow",
            "Centre For Advanced Studies",
            "Integral University",
            "School of Management Sciences, Lucknow",
            "Shri Ramswaroop Memorial College of Engineering & Management"
        ],
        "mathura": ["Sanskriti University"],
        "meerut": [
            "Dewan V S Institute of Engineering and Technology",
            "Iimt Engineering College, Meerut",
            "IIMT University Meerut",
            "Meerut Institute of Engineering & Technology",
            "Meerut Institute Of Technology, Baral, Partapur, Meerut"
        ],
        "moradabad": [
            "MORADABAD INSTITUTE OF TECHNOLOGY",
            "Teerthanker Mahaveer University"
        ],
        "noida": ["Jaypee Institute of Information Technology"],
        "prayagraj": [
            "Motilal Nehru National Institute of Technology",
            "Sam Higginbottom Institute of Agriculture, Technology & Sciences",
            "United College of Engineering and Research"
        ],
        "prayagraj (allahabad)": [
            "Indian Institute of Information Technology Allahabad"
        ],
        "saharanpur": ["Glocal University"],
        "sitapur": [
            "SACRED HEART INSTITUTE OF MANAGAMENT AND TECHNOLOGY, SITAPUR"
        ],
        "sonbhadra": ["Rajkiya engineering college, sonbhadra"],
        "varanasi": [
            "Indian Institute of Technology (Banaras Hindu University) Varanasi",
            "Kashi Institute Of Technology"
        ]
    },
    "uttarakhand": {
        "almora": ["Bipin Tripathi Kumaon Institute of Technology"],
        "dehradun": [
            "Dev Bhoomi Institute of Technology",
            "Graphic Era University",
            "J.B. Institute of Technology",
            "Shivalik College of Engg.",
            "Tulas Institute",
            "UPES",
            "Uttaranchal University"
        ],
        "haridwar": ["Gurukul Kangri Vishwavidyalaya"],
        "pauri": ["Govind Ballabh Pant Institute of Engineering & Technology"],
        "roorkee": [
            "Indian Institute of Technology Roorkee",
            "Quantum University",
            "Roorkee College of Engineering",
            "Roorkee Institute of Technology"
        ],
        "srinagar (garhwal)": ["National Institute of Technology Uttarakhand"]
    },
    "west bengal": {
        "asansol": [
            "Asansol Engineering College",
            "Kazi Nazrul University, Asansol"
        ],
        "bankura": ["Mallabhum Institute of Technology 158"],
        "barddhaman": [
            "NSHM Knowledge Campus Durgapur Group of Institutions 273"
        ],
        "bardhaman": ["Dr. B.C. Roy Engineering College, Durgapur"],
        "chinsurah": ["Hooghly Engineering and Technology College"],
        "diamond harbour": ["The Neotia University"],
        "durgapur": [
            "Bengal College of Engineering & Technology",
            "National Institute of Technology Durgapur"
        ],
        "haldia": ["Haldia Institute of Technology"],
        "hooghly": ["ACADEMY OF TECHNOLOGY"],
        "howrah": [
            "MCKV Institute of Engineering",
            "Omdayal Group of Institutions"
        ],
        "hugli": ["Supreme Knowledge Foundation Group of Institutions"],
        "jalpaiguri": ["Jalpaiguri Government Engineering College"],
        "kalyani": [
            "INDIAN INSTITUTE OF INFORMATION TECHNOLOGY, KALYANI",
            "JIS COLLEGE OF ENGINEERING",
            "Kalyani Government Engineering College"
        ],
        "kharagpur": ["Indian Institute of Technology Kharagpur"],
        "kolkata": [
            "Greater Kolkata College of Engineering and Management 236",
            "TECHNO INTERNATIONAL NEW TOWN"
        ],
        "malda": [
            "Ghani Khan Choudhury Institute of Engineering & Technology, Kotwali, Malda"
        ],
        "mogra": ["ABACUS Institute of Engineering and Management"],
        "nadia": ["Maulana Abul Kalam Azad University of Technology"],
        "new town": ["University of Engineering and Management, Kolkata"],
        "north twenty four parganas": [
            "Amity University",
            "Gurunanak Institute Of Technology"
        ],
        "south twenty four parganas": ["TECHNO INTERNATIONAL BATANAGAR"],
        "uluberia": ["Calcutta Institute of Technology 177"]
    }
}
